roofai/README.py
roofai/__init__.py
roofai/__main__.py
roofai/config.env
roofai/env.py
roofai/host.py
roofai/logger.py
roofai/sample.env
roofai/urls.py
roofai/.abcli/abcli.sh
roofai/.abcli/actions.sh
roofai/.abcli/alias.sh
roofai/.abcli/dataset.sh
roofai/.abcli/google_earth.sh
roofai/.abcli/google_maps.sh
roofai/.abcli/install.sh
roofai/.abcli/roboflow.sh
roofai/.abcli/roofAI.sh
roofai/.abcli/semseg.sh
roofai/.abcli/dataset/ingest.sh
roofai/.abcli/dataset/review.sh
roofai/.abcli/google_earth/browse.sh
roofai/.abcli/google_earth/fetch.sh
roofai/.abcli/google_earth/install.sh
roofai/.abcli/google_maps/geocode.sh
roofai/.abcli/google_maps/ingest_dataset.sh
roofai/.abcli/google_maps/predict.sh
roofai/.abcli/google_maps/static_api.sh
roofai/.abcli/roboflow/create_project.sh
roofai/.abcli/roboflow/download.sh
roofai/.abcli/roboflow/status.sh
roofai/.abcli/roboflow/upload.sh
roofai/.abcli/semseg/predict.sh
roofai/.abcli/semseg/train.sh
roofai/.abcli/tests/README.sh
roofai/.abcli/tests/dataset_ingest_and_review.sh
roofai/.abcli/tests/google_earth_browse.sh
roofai/.abcli/tests/google_earth_fetch.sh
roofai/.abcli/tests/google_maps_geocode.sh
roofai/.abcli/tests/google_maps_get_static_image.sh
roofai/.abcli/tests/google_maps_ingest_dataset.sh
roofai/.abcli/tests/google_maps_predict.sh
roofai/.abcli/tests/help.sh
roofai/.abcli/tests/roboflow_create_project.sh
roofai/.abcli/tests/roboflow_download.sh
roofai/.abcli/tests/roboflow_status.sh
roofai/.abcli/tests/semseg_predict.sh
roofai/.abcli/tests/semseg_train.sh
roofai/.abcli/tests/semseg_train_and_predict.sh
roofai/.abcli/tests/version.sh
roofai/dataset/README.py
roofai/dataset/__init__.py
roofai/dataset/__main__.py
roofai/dataset/classes.py
roofai/dataset/sagemaker.py
roofai/dataset/ingest/CamVid.py
roofai/dataset/ingest/__init__.py
roofai/dataset/ingest/from_dataset.py
roofai/google_earth/__init__.py
roofai/google_maps/__init__.py
roofai/google_maps/__main__.py
roofai/google_maps/api/__init__.py
roofai-6.299.1.dist-info/LICENSE
roofai-6.299.1.dist-info/METADATA
roofai-6.299.1.dist-info/WHEEL
roofai-6.299.1.dist-info/top_level.txt
roofai-6.299.1.dist-info/RECORD
