Metadata-Version: 2.2
Name: roofai
Version: 6.299.1
Summary: 🏛️ everything ai about roofs.
Home-page: https://github.com/kamangir/roofai
Author: Arash Abadpour (Kamangir)
Author-email: arash@kamangir.net
License: Public Domain
Classifier: Programming Language :: Python :: 3
Classifier: Programming Language :: Unix Shell
Classifier: License :: Public Domain
Classifier: Operating System :: OS Independent
License-File: LICENSE
Requires-Dist: torch==2.6.0
Requires-Dist: shapely!=2.0.7
Requires-Dist: albumentations[imgaug]
Requires-Dist: efficientnet_pytorch
Requires-Dist: pretrainedmodels
Requires-Dist: segmentation_models_pytorch
Requires-Dist: blueness
Requires-Dist: abcli
Requires-Dist: blueflow
Requires-Dist: geojson
Requires-Dist: geopandas
Requires-Dist: opencv-python
Requires-Dist: scipy
Requires-Dist: kaggle
Requires-Dist: roboflow
Dynamic: author
Dynamic: author-email
Dynamic: classifier
Dynamic: description
Dynamic: description-content-type
Dynamic: home-page
Dynamic: license
Dynamic: requires-dist
Dynamic: summary
